[
  {
    "id": "r1",
    "name": "Jain Burger",
    "address": "Subhash Nagar",
    "cuisine": "Indian",
    "website": "https://www.youtube.com/",
    "description": "aacha hai bhai\r\n"
  },
  {
    "id": "r2",
    "name": "test ",
    "address": "test",
    "cuisine": "chinese",
    "website": "https://mytest.com",
    "description": "test is success"
  },
  {
    "id": "r3",
    "name": "restaurant 3",
    "address": "resta",
    "cuisine": "mexican",
    "website": "https:/apnatimeaagya.com",
    "description": "oh yes khaana aacha tha"
  },
  {
    "name": "test 4",
    "address": "test",
    "cuisine": "Indian",
    "website": "https://www.test.com",
    "description": "test",
    "id": "4ff3e621-1375-4eed-933e-6a72426820b6"
  }
]
